dj3fb/__init__.py
dj3fb/faker_utils.py
dj3fb/management/__init__.py
dj3fb/management/commands/__init__.py
dj3fb/management/commands/generate_factories.py
dj3fb/services/__init__.py
dj3fb/services/generate_factories_service/__init__.py
dj3fb/services/generate_factories_service/factory_template.py
dj3fb/services/generate_factories_service/field_template_manager.py
dj3fb/services/generate_factories_service/field_templates.py
dj3fb/services/generate_factories_service/generate_factories_service.py
dj3fb-0.3.0.dist-info/LICENSE
dj3fb-0.3.0.dist-info/METADATA
dj3fb-0.3.0.dist-info/WHEEL
dj3fb-0.3.0.dist-info/top_level.txt
dj3fb-0.3.0.dist-info/RECORD
