Metadata-Version: 2.1
Name: dj3fb
Version: 0.3.0
Summary: dj3fb can generate DjangoModelFactory for your django models by using factory_boy.
Author-email: three-kinds <3179158552@qq.com>
License: MIT
Project-URL: Homepage, https://github.com/three-kinds/dj3fb
Project-URL: Source, https://github.com/three-kinds/dj3fb
Classifier: Development Status :: 2 - Pre-Alpha
Classifier: Intended Audience :: Developers
Classifier: License :: OSI Approved :: Apache Software License
Classifier: Operating System :: OS Independent
Classifier: Programming Language :: Python
Classifier: Programming Language :: Python :: 3
Classifier: Programming Language :: Python :: 3 :: Only
Classifier: Programming Language :: Python :: 3.10
Classifier: Programming Language :: Python :: 3.11
Classifier: Programming Language :: Python :: 3.12
Classifier: Programming Language :: Python :: 3.13
Classifier: Topic :: Software Development :: Libraries :: Python Modules
Classifier: Framework :: Django
Requires-Python: >=3.10
License-File: LICENSE
Requires-Dist: django
Requires-Dist: faker
Requires-Dist: factory-boy
Requires-Dist: a3py
Requires-Dist: lazy-object-proxy
